flet_ft/__init__.py
flet_ft/ft_ui_loader.py
flet_ft/screen_menager.py
fletft-0.0.5.dist-info/METADATA
fletft-0.0.5.dist-info/WHEEL
fletft-0.0.5.dist-info/top_level.txt
fletft-0.0.5.dist-info/RECORD
