Metadata-Version: 2.4
Name: fletft
Version: 0.0.5
Summary: Flet add .ft and screen menager
Author-email: Przemek <email@example.com>
Requires-Python: >=3.8
Requires-Dist: flet
Requires-Dist: PyYAML
